mori_ssh
