Metadata-Version: 1.0
Name: mori-ssh
Version: 0.1.4
Summary: Mori SSH pack
Home-page: https://github.com/moriW/mssh
Author: moridisa
Author-email: moridisa@moridisa.cn
License: MIT
Platform: UNKNOWN
